README.txt
gitweb.py
setup.cfg
setup.py
subprocessio.py
GitWeb.egg-info/PKG-INFO
GitWeb.egg-info/SOURCES.txt
GitWeb.egg-info/dependency_links.txt
GitWeb.egg-info/entry_points.txt
GitWeb.egg-info/not-zip-safe
GitWeb.egg-info/requires.txt
GitWeb.egg-info/top_level.txt