Metadata-Version: 1.0
Name: GitWeb
Version: 0.4
Summary: WSGI application to serve a git repository
Home-page: https://github.com/gawel/GitWeb
Author: Gael Pasgrimaud
Author-email: gael@gawel.org
License: GPL
Keywords: web
Platform: UNKNOWN
Classifier: Programming Language :: Python
Classifier: Topic :: Internet :: WWW/HTTP
Classifier: Topic :: Internet :: WWW/HTTP :: WSGI :: Application
